djangocms_geoplaceholder/__init__.py
djangocms_geoplaceholder/admin.py
djangocms_geoplaceholder/apps.py
djangocms_geoplaceholder/cms_plugins.py
djangocms_geoplaceholder/forms.py
djangocms_geoplaceholder/models.py
djangocms_geoplaceholder/tests.py
djangocms_geoplaceholder/views.py
djangocms_geoplaceholder/locale/ru/LC_MESSAGES/django.mo
djangocms_geoplaceholder/locale/ru/LC_MESSAGES/django.po
djangocms_geoplaceholder/migrations/0001_initial.py
djangocms_geoplaceholder/migrations/0002_auto_20190728_2026.py
djangocms_geoplaceholder/migrations/__init__.py
djangocms_geoplaceholder/templates/plugins/geo_placeholder.html
djangocms_geoplaceholder-1.1.0.dist-info/METADATA
djangocms_geoplaceholder-1.1.0.dist-info/WHEEL
djangocms_geoplaceholder-1.1.0.dist-info/top_level.txt
djangocms_geoplaceholder-1.1.0.dist-info/RECORD
