Metadata-Version: 2.1
Name: djangocms-geoplaceholder
Version: 1.1.0
Summary: Plugin for Django CMS that renders child plugins only for visitors from certain locations identified by GeoIP
Home-page: https://bitbucket.org/TheDeadOne/djangocms-geoplaceholder/
Author: Sergey Gornostaev
Author-email: sergey@gornostaev.dev
License: BSD license
Platform: UNKNOWN
Classifier: Development Status :: 5 - Production/Stable
Classifier: Environment :: Web Environment
Classifier: Framework :: Django
Classifier: Intended Audience :: Developers
Classifier: License :: OSI Approved :: BSD License
Classifier: Programming Language :: Python
Classifier: Programming Language :: Python :: 2.7
Classifier: Programming Language :: Python :: 3.5
Classifier: Programming Language :: Python :: 3.6
Classifier: Programming Language :: Python :: 3.7
Classifier: Topic :: Software Development :: Libraries :: Python Modules
Classifier: Natural Language :: Russian
Requires-Dist: django-cms
Requires-Dist: django-geoip
